scuttle/__init__.py
scuttle/wrapper.py
scuttle/versions/__init__.py
scuttle/versions/base.py
scuttle/versions/v1.py
python_scuttle-0.3.1.dist-info/LICENSE
python_scuttle-0.3.1.dist-info/METADATA
python_scuttle-0.3.1.dist-info/WHEEL
python_scuttle-0.3.1.dist-info/top_level.txt
python_scuttle-0.3.1.dist-info/RECORD
