Metadata-Version: 2.1
Name: python-scuttle
Version: 0.3.1
Summary: Python wrapper for SCUTTLE API.
Home-page: http://github.com/scuttle/python-scuttle
Author: Ross Williams
Author-email: ross@rossjrw.com
License: MIT
Platform: UNKNOWN
Classifier: Programming Language :: Python :: 3.8
Classifier: Intended Audience :: Developers
Classifier: Development Status :: 4 - Beta
Classifier: License :: OSI Approved :: MIT License
Requires-Python: >=3.8
Requires-Dist: requests
Requires-Dist: wrapt
